{"ref":"aa1d6021-79a1-4360-9813-2f34c3fe9a41","content":"{\"version\":1,\"machineId\":\"47b3eb3a-0cf2-40f7-b9ed-a2112135dafc\",\"content\":\"{\\\"sql.json\\\":\\\"{\\\\n\\\\t// Place your snippets for sql here. Each snippet is defined under a snippet name and has a prefix, body and \\\\n\\\\t// description. The prefix is what is used to trigger the snippet and the body will be expanded and inserted. Possible variables are:\\\\n\\\\t// $1, $2 for tab stops, $0 for the final cursor position, and ${1:label}, ${2:another} for placeholders. Placeholders with the \\\\n\\\\t// same ids are connected.\\\\n\\\\t// Example:\\\\n\\\\t// \\\\\\\"Print to console\\\\\\\": {\\\\n\\\\t// \\\\t\\\\\\\"prefix\\\\\\\": \\\\\\\"log\\\\\\\",\\\\n\\\\t// \\\\t\\\\\\\"body\\\\\\\": [\\\\n\\\\t// \\\\t\\\\t\\\\\\\"console.log('$1');\\\\\\\",\\\\n\\\\t// \\\\t\\\\t\\\\\\\"$2\\\\\\\"\\\\n\\\\t// \\\\t],\\\\n\\\\t// \\\\t\\\\\\\"description\\\\\\\": \\\\\\\"Log output to console\\\\\\\"\\\\n\\\\t// }\\\\n}\\\",\\\"javascript.json\\\":\\\"{\\\\n\\\\t// Place your snippets for javascript here. Each snippet is defined under a snippet name and has a prefix, body and\\\\n\\\\t// description. The prefix is what is used to trigger the snippet and the body will be expanded and inserted. Possible variables are:\\\\n\\\\t// $1, $2 for tab stops, $0 for the final cursor position, and ${1:label}, ${2:another} for placeholders. Placeholders with the\\\\n\\\\t// same ids are connected.\\\\n\\\\t// Example:\\\\n\\\\t\\\\\\\"NODE_ENV DEVELOPMENT\\\\\\\": {\\\\n\\\\t\\\\t\\\\\\\"prefix\\\\\\\": \\\\\\\"envD\\\\\\\",\\\\n\\\\t\\\\t\\\\\\\"body\\\\\\\": [\\\\n\\\\t\\\\t\\\\t\\\\\\\"if (process.env.NODE_ENV === 'development') {\\\\\\\",\\\\n\\\\t\\\\t\\\\t\\\\\\\"  $1\\\\\\\",\\\\n\\\\t\\\\t\\\\t\\\\\\\"}\\\\\\\"\\\\n\\\\t\\\\t],\\\\n\\\\t\\\\t\\\\\\\"description\\\\\\\": \\\\\\\"development env\\\\\\\"\\\\n\\\\t},\\\\n\\\\t\\\\\\\"NODE_ENV PRODUCTION\\\\\\\": {\\\\n\\\\t\\\\t\\\\\\\"prefix\\\\\\\": \\\\\\\"envP\\\\\\\",\\\\n\\\\t\\\\t\\\\\\\"body\\\\\\\": [\\\\n\\\\t\\\\t\\\\t\\\\\\\"if (process.env.NODE_ENV === 'production') {\\\\\\\",\\\\n\\\\t\\\\t\\\\t\\\\\\\"  $1\\\\\\\",\\\\n\\\\t\\\\t\\\\t\\\\\\\"}\\\\\\\"\\\\n\\\\t\\\\t],\\\\n\\\\t\\\\t\\\\\\\"description\\\\\\\": \\\\\\\"production env\\\\\\\"\\\\n\\\\t}\\\\n}\\\",\\\"julia.json\\\":\\\"{\\\\n\\\\t// Place your snippets for julia here. Each snippet is defined under a snippet name and has a prefix, body and \\\\n\\\\t// description. The prefix is what is used to trigger the snippet and the body will be expanded and inserted. Possible variables are:\\\\n\\\\t// $1, $2 for tab stops, $0 for the final cursor position, and ${1:label}, ${2:another} for placeholders. Placeholders with the \\\\n\\\\t// same ids are connected.\\\\n\\\\t// Example:\\\\n\\\\t// \\\\\\\"Print to console\\\\\\\": {\\\\n\\\\t// \\\\t\\\\\\\"prefix\\\\\\\": \\\\\\\"log\\\\\\\",\\\\n\\\\t// \\\\t\\\\\\\"body\\\\\\\": [\\\\n\\\\t// \\\\t\\\\t\\\\\\\"console.log('$1');\\\\\\\",\\\\n\\\\t// \\\\t\\\\t\\\\\\\"$2\\\\\\\"\\\\n\\\\t// \\\\t],\\\\n\\\\t// \\\\t\\\\\\\"description\\\\\\\": \\\\\\\"Log output to console\\\\\\\"\\\\n\\\\t// }\\\\n}\\\",\\\"vue-html.json\\\":\\\"{\\\\n\\\\t// Place your snippets for vue-html here. Each snippet is defined under a snippet name and has a prefix, body and\\\\n\\\\t// description. The prefix is what is used to trigger the snippet and the body will be expanded and inserted. Possible variables are:\\\\n\\\\t// $1, $2 for tab stops, $0 for the final cursor position, and ${1:label}, ${2:another} for placeholders. Placeholders with the\\\\n\\\\t// same ids are connected.\\\\n\\\\t// Example:\\\\n\\\\t\\\\\\\":class\\\\\\\": {\\\\n\\\\t\\\\t\\\\\\\"prefix\\\\\\\": \\\\\\\":class\\\\\\\",\\\\n\\\\t\\\\t\\\\\\\"body\\\\\\\": [\\\\n\\\\t\\\\t\\\\t\\\\\\\":class=\\\\\\\\\\\\\\\"{ ${1:calssName}: ${2:Boolean}}\\\\\\\\\\\\\\\"\\\\\\\"\\\\n\\\\t\\\\t],\\\\n\\\\t\\\\t\\\\\\\"description\\\\\\\": \\\\\\\":class\\\\\\\"\\\\n\\\\t},\\\\n\\\\t\\\\\\\"NODE_ENV DEVELOPMENT\\\\\\\": {\\\\n\\\\t\\\\t\\\\\\\"prefix\\\\\\\": \\\\\\\"envD\\\\\\\",\\\\n\\\\t\\\\t\\\\\\\"body\\\\\\\": [\\\\n\\\\t\\\\t\\\\t\\\\\\\"process.env.NODE_ENV === 'development'\\\\\\\",\\\\n\\\\t\\\\t],\\\\n\\\\t\\\\t\\\\\\\"description\\\\\\\": \\\\\\\"development env\\\\\\\"\\\\n\\\\t},\\\\n\\\\t\\\\\\\"NODE_ENV PRODUCTION\\\\\\\": {\\\\n\\\\t\\\\t\\\\\\\"prefix\\\\\\\": \\\\\\\"envP\\\\\\\",\\\\n\\\\t\\\\t\\\\\\\"body\\\\\\\": [\\\\n\\\\t\\\\t\\\\t\\\\\\\"process.env.NODE_ENV === 'production'\\\\\\\",\\\\n\\\\t\\\\t],\\\\n\\\\t\\\\t\\\\\\\"description\\\\\\\": \\\\\\\"production env\\\\\\\"\\\\n\\\\t},\\\\n\\\\t\\\\\\\"valform\\\\\\\": {\\\\n\\\\t\\\\t\\\\\\\"prefix\\\\\\\": \\\\\\\"valform\\\\\\\",\\\\n\\\\t\\\\t\\\\\\\"body\\\\\\\": [\\\\n\\\\t\\\\t\\\\t\\\\\\\"this.refs.$1.validate(v => {\\\\\\\",\\\\n\\\\t\\\\t\\\\t\\\\\\\"  if (!v) {\\\\\\\",\\\\n\\\\t\\\\t\\\\t\\\\\\\"    return\\\\\\\",\\\\n\\\\t\\\\t\\\\t\\\\\\\"  }\\\\\\\",\\\\n\\\\t\\\\t\\\\t\\\\\\\"  $2\\\\\\\",\\\\n\\\\t\\\\t\\\\t\\\\\\\"})\\\\\\\"\\\\n\\\\t\\\\t],\\\\n\\\\t\\\\t\\\\\\\"description\\\\\\\": \\\\\\\"element form validate\\\\\\\"\\\\n\\\\t},\\\\n\\\\t\\\\\\\"vxe-grid\\\\\\\": {\\\\n\\\\t\\\\t\\\\\\\"prefix\\\\\\\": \\\\\\\"egrid\\\\\\\",\\\\n\\\\t\\\\t\\\\\\\"body\\\\\\\": [\\\\n\\\\t\\\\t\\\\t\\\\\\\"<el-main\\\\\\\",\\\\n\\\\t\\\\t\\\\t\\\\\\\"  height=\\\\\\\\\\\\\\\"\\\\\\\\\\\\\\\"\\\\\\\",\\\\n\\\\t\\\\t\\\\t\\\\\\\"  style=\\\\\\\\\\\\\\\"height: calc(100% - 102px); padding: 0px 20px\\\\\\\\\\\\\\\"\\\\\\\",\\\\n\\\\t\\\\t\\\\t\\\\\\\">\\\\\\\",\\\\n\\\\t\\\\t\\\\t\\\\\\\"  <!-- Main content -->\\\\\\\",\\\\n\\\\t\\\\t\\\\t\\\\\\\"  <vxe-grid\\\\\\\",\\\\n\\\\t\\\\t\\\\t\\\\\\\"    ref=\\\\\\\\\\\\\\\"xGrid\\\\\\\\\\\\\\\"\\\\\\\",\\\\n\\\\t\\\\t\\\\t\\\\\\\"    border\\\\\\\",\\\\n\\\\t\\\\t\\\\t\\\\\\\"    resizable\\\\\\\",\\\\n\\\\t\\\\t\\\\t\\\\\\\"    height=\\\\\\\\\\\\\\\"auto\\\\\\\\\\\\\\\"\\\\\\\",\\\\n\\\\t\\\\t\\\\t\\\\\\\"    align=\\\\\\\\\\\\\\\"center\\\\\\\\\\\\\\\"\\\\\\\",\\\\n\\\\t\\\\t\\\\t\\\\\\\"    :loading=\\\\\\\\\\\\\\\"loading\\\\\\\\\\\\\\\"\\\\\\\",\\\\n\\\\t\\\\t\\\\t\\\\\\\"    :data=\\\\\\\\\\\\\\\"tableData\\\\\\\\\\\\\\\"\\\\\\\",\\\\n\\\\t\\\\t\\\\t\\\\\\\"    :columns=\\\\\\\\\\\\\\\"tableColumn\\\\\\\\\\\\\\\"\\\\\\\",\\\\n\\\\t\\\\t\\\\t\\\\\\\"    :sort-config=\\\\\\\\\\\\\\\"{\\\\\\\",\\\\n\\\\t\\\\t\\\\t\\\\\\\"      trigger: 'cell',\\\\\\\",\\\\n\\\\t\\\\t\\\\t\\\\\\\"      defaultSort: { field: 'age', order: 'desc' },\\\\\\\",\\\\n\\\\t\\\\t\\\\t\\\\\\\"      orders: ['desc', 'asc', null],\\\\\\\",\\\\n\\\\t\\\\t\\\\t\\\\\\\"    }\\\\\\\\\\\\\\\"\\\\\\\",\\\\n\\\\t\\\\t\\\\t\\\\\\\"    @sort-change=\\\\\\\\\\\\\\\"sortChangeEvent\\\\\\\\\\\\\\\"\\\\\\\",\\\\n\\\\t\\\\t\\\\t\\\\\\\"  >\\\\\\\",\\\\n\\\\t\\\\t\\\\t\\\\\\\"    <template v-slot:operate=\\\\\\\\\\\\\\\"{ row }\\\\\\\\\\\\\\\">\\\\\\\",\\\\n\\\\t\\\\t\\\\t\\\\\\\"        <el-popconfirm\\\\\\\",\\\\n\\\\t\\\\t\\\\t\\\\\\\"        :title=\\\\\\\\\\\\\\\"`确定删除用户【${row.user_name}】吗？`\\\\\\\\\\\\\\\"\\\\\\\",\\\\n\\\\t\\\\t\\\\t\\\\\\\"        @onConfirm=\\\\\\\\\\\\\\\"delUser(row)\\\\\\\\\\\\\\\"\\\\\\\",\\\\n\\\\t\\\\t\\\\t\\\\\\\"      >\\\\\\\",\\\\n\\\\t\\\\t\\\\t\\\\\\\"        <vxe-button\\\\\\\",\\\\n\\\\t\\\\t\\\\t\\\\\\\"          title=\\\\\\\\\\\\\\\"删除\\\\\\\\\\\\\\\"\\\\\\\",\\\\n\\\\t\\\\t\\\\t\\\\\\\"          circle\\\\\\\",\\\\n\\\\t\\\\t\\\\t\\\\\\\"          type=\\\\\\\\\\\\\\\"danger\\\\\\\\\\\\\\\"\\\\\\\",\\\\n\\\\t\\\\t\\\\t\\\\\\\"          icon=\\\\\\\\\\\\\\\"el-icon-delete\\\\\\\\\\\\\\\"\\\\\\\",\\\\n\\\\t\\\\t\\\\t\\\\\\\"          slot=\\\\\\\\\\\\\\\"reference\\\\\\\\\\\\\\\"\\\\\\\",\\\\n\\\\t\\\\t\\\\t\\\\\\\"        ></vxe-button>\\\\\\\",\\\\n\\\\t\\\\t\\\\t\\\\\\\"      </el-popconfirm>\\\\\\\",\\\\n\\\\t\\\\t\\\\t\\\\\\\"    </template>\\\\\\\",\\\\n\\\\t\\\\t\\\\t\\\\\\\"  </vxe-grid>\\\\\\\",\\\\n\\\\t\\\\t\\\\t\\\\\\\"</el-main>\\\\\\\",\\\\n\\\\t\\\\t\\\\t\\\\\\\"<el-footer height=\\\\\\\\\\\\\\\"48px\\\\\\\\\\\\\\\">\\\\\\\",\\\\n\\\\t\\\\t\\\\t\\\\\\\"  <!-- Footer content -->\\\\\\\",\\\\n\\\\t\\\\t\\\\t\\\\\\\"  <vxe-pager\\\\\\\",\\\\n\\\\t\\\\t\\\\t\\\\\\\"    :current-page=\\\\\\\\\\\\\\\"tablePage.currentPage\\\\\\\\\\\\\\\"\\\\\\\",\\\\n\\\\t\\\\t\\\\t\\\\\\\"    :page-size=\\\\\\\\\\\\\\\"tablePage.pageSize\\\\\\\\\\\\\\\"\\\\\\\",\\\\n\\\\t\\\\t\\\\t\\\\\\\"    :total=\\\\\\\\\\\\\\\"tablePage.totalResult\\\\\\\\\\\\\\\"\\\\\\\",\\\\n\\\\t\\\\t\\\\t\\\\\\\"    :layouts=\\\\\\\\\\\\\\\"[\\\\\\\",\\\\n\\\\t\\\\t\\\\t\\\\\\\"      'PrevPage',\\\\\\\",\\\\n\\\\t\\\\t\\\\t\\\\\\\"      'JumpNumber',\\\\\\\",\\\\n\\\\t\\\\t\\\\t\\\\\\\"      'NextPage',\\\\\\\",\\\\n\\\\t\\\\t\\\\t\\\\\\\"      'FullJump',\\\\\\\",\\\\n\\\\t\\\\t\\\\t\\\\\\\"      'Sizes',\\\\\\\",\\\\n\\\\t\\\\t\\\\t\\\\\\\"      'Total',\\\\\\\",\\\\n\\\\t\\\\t\\\\t\\\\\\\"    ]\\\\\\\\\\\\\\\"\\\\\\\",\\\\n\\\\t\\\\t\\\\t\\\\\\\"    @page-change=\\\\\\\\\\\\\\\"handlePageChange\\\\\\\\\\\\\\\"\\\\\\\",\\\\n\\\\t\\\\t\\\\t\\\\\\\"  />\\\\\\\",\\\\n\\\\t\\\\t\\\\t\\\\\\\"</el-footer>\\\\\\\",\\\\n\\\\t\\\\t],\\\\n\\\\t\\\\t\\\\\\\"description\\\\\\\": \\\\\\\"生成表格 vxe-grid\\\\\\\"\\\\n\\\\t},\\\\n\\\\t\\\\\\\"el-container\\\\\\\": {\\\\n\\\\t\\\\t\\\\\\\"prefix\\\\\\\": \\\\\\\"elc\\\\\\\",\\\\n\\\\t\\\\t\\\\\\\"body\\\\\\\": [\\\\n\\\\t\\\\t\\\\t\\\\\\\"   <el-container direction=\\\\\\\\\\\\\\\"vertical\\\\\\\\\\\\\\\" style=\\\\\\\\\\\\\\\"height: calc(100vh - 50px)\\\\\\\\\\\\\\\">\\\\\\\",\\\\n\\\\t\\\\t\\\\t\\\\\\\"     <el-header height=\\\\\\\\\\\\\\\"54px\\\\\\\\\\\\\\\">\\\\\\\",\\\\n\\\\t\\\\t\\\\t\\\\\\\"       <!-- Header area -->$1\\\\\\\",\\\\n\\\\t\\\\t\\\\t\\\\\\\"     </el-header>\\\\\\\",\\\\n\\\\t\\\\t\\\\t\\\\\\\"     <el-container direction=\\\\\\\\\\\\\\\"horizontal\\\\\\\\\\\\\\\">\\\\\\\",\\\\n\\\\t\\\\t\\\\t\\\\\\\"       <el-aside width=\\\\\\\\\\\\\\\"200px\\\\\\\\\\\\\\\">\\\\\\\",\\\\n\\\\t\\\\t\\\\t\\\\\\\"         <!-- Aside area -->\\\\\\\",\\\\n\\\\t\\\\t\\\\t\\\\\\\"       </el-aside>\\\\\\\",\\\\n\\\\t\\\\t\\\\t\\\\\\\"       <el-container direction=\\\\\\\\\\\\\\\"vertical\\\\\\\\\\\\\\\">\\\\\\\",\\\\n\\\\t\\\\t\\\\t\\\\\\\"         <el-main height=\\\\\\\\\\\\\\\"\\\\\\\\\\\\\\\">\\\\\\\",\\\\n\\\\t\\\\t\\\\t\\\\\\\"           <!-- Main area -->$2\\\\\\\",\\\\n\\\\t\\\\t\\\\t\\\\\\\"         </el-main>\\\\\\\",\\\\n\\\\t\\\\t\\\\t\\\\\\\"         <el-footer height=\\\\\\\\\\\\\\\"\\\\\\\\\\\\\\\">\\\\\\\",\\\\n\\\\t\\\\t\\\\t\\\\\\\"           <!-- Footer area -->$3\\\\\\\",\\\\n\\\\t\\\\t\\\\t\\\\\\\"         </el-footer>\\\\\\\",\\\\n\\\\t\\\\t\\\\t\\\\\\\"       </el-container>\\\\\\\",\\\\n\\\\t\\\\t\\\\t\\\\\\\"     </el-container>\\\\\\\",\\\\n\\\\t\\\\t\\\\t\\\\\\\"   </el-container>\\\\\\\",\\\\n\\\\t\\\\t],\\\\n\\\\t\\\\t\\\\\\\"description\\\\\\\": \\\\\\\"容器布局 container aside footer\\\\\\\"\\\\n\\\\t},\\\\n\\\\t\\\\\\\"el-head\\\\\\\": {\\\\n\\\\t\\\\t\\\\\\\"prefix\\\\\\\": \\\\\\\"elh\\\\\\\",\\\\n\\\\t\\\\t\\\\\\\"body\\\\\\\": [\\\\n\\\\t\\\\t\\\\t\\\\\\\"  <el-header height=\\\\\\\\\\\\\\\"54px\\\\\\\\\\\\\\\">\\\\\\\",\\\\n\\\\t\\\\t\\\\t\\\\\\\"    <el-row :gutter=\\\\\\\\\\\\\\\"20\\\\\\\\\\\\\\\" type=\\\\\\\\\\\\\\\"flex\\\\\\\\\\\\\\\" justify=\\\\\\\\\\\\\\\"space-between\\\\\\\\\\\\\\\">\\\\\\\",\\\\n\\\\t\\\\t\\\\t\\\\\\\"      <el-col :span=\\\\\\\\\\\\\\\"12\\\\\\\\\\\\\\\" :offset=\\\\\\\\\\\\\\\"0\\\\\\\\\\\\\\\">\\\\\\\",\\\\n\\\\t\\\\t\\\\t\\\\\\\"        <el-row type=\\\\\\\\\\\\\\\"flex\\\\\\\\\\\\\\\" justify=\\\\\\\\\\\\\\\"start\\\\\\\\\\\\\\\">\\\\\\\",\\\\n\\\\t\\\\t\\\\t\\\\\\\"          <el-input v-model=\\\\\\\\\\\\\\\"\\\\\\\\\\\\\\\" size=\\\\\\\\\\\\\\\"medium\\\\\\\\\\\\\\\" placeholder=\\\\\\\\\\\\\\\"请输入账号\\\\\\\\\\\\\\\">\\\\\\\",\\\\n\\\\t\\\\t\\\\t\\\\\\\"          <el-button slot=\\\\\\\\\\\\\\\"append\\\\\\\\\\\\\\\" icon=\\\\\\\\\\\\\\\"el-icon-search\\\\\\\\\\\\\\\" @click=\\\\\\\\\\\\\\\"\\\\\\\\\\\\\\\"/></el-input>$1\\\\\\\",\\\\n\\\\t\\\\t\\\\t\\\\\\\"        </el-row>\\\\\\\",\\\\n\\\\t\\\\t\\\\t\\\\\\\"      </el-col>\\\\\\\",\\\\n\\\\t\\\\t\\\\t\\\\\\\"      <el-col :span=\\\\\\\\\\\\\\\"12\\\\\\\\\\\\\\\" :offset=\\\\\\\\\\\\\\\"0\\\\\\\\\\\\\\\">\\\\\\\",\\\\n\\\\t\\\\t\\\\t\\\\\\\"        <el-row type=\\\\\\\\\\\\\\\"flex\\\\\\\\\\\\\\\" justify=\\\\\\\\\\\\\\\"end\\\\\\\\\\\\\\\">\\\\\\\",\\\\n\\\\t\\\\t\\\\t\\\\\\\"          <el-button size=\\\\\\\\\\\\\\\"medium\\\\\\\\\\\\\\\" type=\\\\\\\\\\\\\\\"primary\\\\\\\\\\\\\\\" @click=\\\\\\\\\\\\\\\"\\\\\\\\\\\\\\\">新增用户</el-button>\\\\\\\",\\\\n\\\\t\\\\t\\\\t\\\\\\\"        </el-row>\\\\\\\",\\\\n\\\\t\\\\t\\\\t\\\\\\\"      </el-col>\\\\\\\",\\\\n\\\\t\\\\t\\\\t\\\\\\\"    </el-row>\\\\\\\",\\\\n\\\\t\\\\t\\\\t\\\\\\\"  </el-header>\\\\\\\",\\\\n\\\\t\\\\t],\\\\n\\\\t\\\\t\\\\\\\"description\\\\\\\": \\\\\\\"容器布局 container aside footer\\\\\\\"\\\\n\\\\t},\\\\n\\\\t\\\\\\\"scss\\\\\\\": {\\\\n\\\\t\\\\t\\\\\\\"prefix\\\\\\\": \\\\\\\"scss\\\\\\\",\\\\n\\\\t\\\\t\\\\\\\"body\\\\\\\": [\\\\n\\\\t\\\\t\\\\t\\\\\\\"<style lang=\\\\\\\\\\\\\\\"scss\\\\\\\\\\\\\\\" scoped>\\\\\\\",\\\\n\\\\t\\\\t\\\\t\\\\\\\"   $1\\\\\\\",\\\\n\\\\t\\\\t\\\\t\\\\\\\"</style>\\\\\\\"\\\\n\\\\t\\\\t]\\\\n\\\\t},\\\\n\\\\t\\\\\\\"computer\\\\\\\": {\\\\n\\\\t\\\\t\\\\\\\"prefix\\\\\\\": \\\\\\\"cmp\\\\\\\",\\\\n\\\\t\\\\t\\\\\\\"body\\\\\\\": [\\\\n\\\\t\\\\t\\\\t\\\\\\\"computed: {\\\\\\\",\\\\n\\\\t\\\\t\\\\t\\\\\\\"  $1: {\\\\\\\",\\\\n\\\\t\\\\t\\\\t\\\\\\\"       get: function () {\\\\\\\",\\\\n\\\\t\\\\t\\\\t\\\\\\\"         return this.$2\\\\\\\",\\\\n\\\\t\\\\t\\\\t\\\\\\\"       },\\\\\\\",\\\\n\\\\t\\\\t\\\\t\\\\\\\"       set: function (v) {\\\\\\\",\\\\n\\\\t\\\\t\\\\t\\\\\\\"         this.$3 = v\\\\\\\",\\\\n\\\\t\\\\t\\\\t\\\\\\\"       }\\\\\\\",\\\\n\\\\t\\\\t\\\\t\\\\\\\"    }\\\\\\\",\\\\n\\\\t\\\\t\\\\t\\\\\\\"},\\\\\\\",\\\\n\\\\t\\\\t]\\\\n\\\\t},\\\\n\\\\t\\\\\\\"CMF\\\\\\\": {\\\\n\\\\t\\\\t\\\\\\\"prefix\\\\\\\": \\\\\\\"CMF\\\\\\\",\\\\n\\\\t\\\\t\\\\\\\"body\\\\\\\": [\\\\n\\\\t\\\\t\\\\t\\\\\\\"// FUNCTION: $1\\\\\\\"\\\\n\\\\t\\\\t],\\\\n\\\\t\\\\t\\\\\\\"description\\\\\\\": \\\\\\\"方法标识 注释高亮\\\\\\\"\\\\n\\\\t}\\\\n}\\\",\\\"vue-postcss.json\\\":\\\"{\\\\n\\\\t// Place your snippets for vue-postcss here. Each snippet is defined under a snippet name and has a prefix, body and \\\\n\\\\t// description. The prefix is what is used to trigger the snippet and the body will be expanded and inserted. Possible variables are:\\\\n\\\\t// $1, $2 for tab stops, $0 for the final cursor position, and ${1:label}, ${2:another} for placeholders. Placeholders with the \\\\n\\\\t// same ids are connected.\\\\n\\\\t// Example:\\\\n\\\\t// \\\\\\\"Print to console\\\\\\\": {\\\\n\\\\t// \\\\t\\\\\\\"prefix\\\\\\\": \\\\\\\"log\\\\\\\",\\\\n\\\\t// \\\\t\\\\\\\"body\\\\\\\": [\\\\n\\\\t// \\\\t\\\\t\\\\\\\"console.log('$1');\\\\\\\",\\\\n\\\\t// \\\\t\\\\t\\\\\\\"$2\\\\\\\"\\\\n\\\\t// \\\\t],\\\\n\\\\t// \\\\t\\\\\\\"description\\\\\\\": \\\\\\\"Log output to console\\\\\\\"\\\\n\\\\t// }\\\\n}\\\"}\"}"}